updatefromgit/__init__.py
updatefromgit/gitfunctions.py
updatefromgit/update_linked_services.py
updatefromgit-2.0.5.dist-info/LICENSE
updatefromgit-2.0.5.dist-info/METADATA
updatefromgit-2.0.5.dist-info/WHEEL
updatefromgit-2.0.5.dist-info/top_level.txt
updatefromgit-2.0.5.dist-info/RECORD
