Metadata-Version: 2.1
Name: updatefromgit
Version: 2.0.5
Summary: Update Fabric Workspace From Git Repo using A user with Email And Password
Author-email: Muhammad Samy <muhssamy@gmail.com>
Maintainer-email: Muhammad Samy <muhssamy@gmail.com>
License: MIT License
Project-URL: Repository, https://github.com/muhssamy/updatefromgit
Keywords: python,updatefromgit,Microsoft Fabric
Classifier: Development Status :: 4 - Beta
Classifier: Programming Language :: Python
Classifier: Operating System :: OS Independent
Requires-Python: >=3.6
License-File: LICENSE
Requires-Dist: msal
Requires-Dist: azlog
